jujube_pill/__init__.py
liliyishsf-0.0.1.dist-info/DESCRIPTION.rst
liliyishsf-0.0.1.dist-info/METADATA
liliyishsf-0.0.1.dist-info/RECORD
liliyishsf-0.0.1.dist-info/WHEEL
liliyishsf-0.0.1.dist-info/entry_points.txt
liliyishsf-0.0.1.dist-info/metadata.json
liliyishsf-0.0.1.dist-info/top_level.txt
