Metadata-Version: 2.0
Name: liliyishsf
Version: 0.0.1
Summary: 吃枣药丸
Home-page: https://zhuanlan.zhihu.com/p/26159930
Author: xlzd
Author-email: l2652856629@163.org
License: UNKNOWN
Platform: UNKNOWN
